py_dreambooth/__init__.py
py_dreambooth/__version__.py
py_dreambooth/dataset.py
py_dreambooth/model.py
py_dreambooth/predictor.py
py_dreambooth/trainer.py
py_dreambooth/scripts/__init__.py
py_dreambooth/scripts/infer/__init__.py
py_dreambooth/scripts/infer/sd_dreambooth/__init__.py
py_dreambooth/scripts/infer/sd_dreambooth/inference.py
py_dreambooth/scripts/infer/sd_dreambooth/requirements.txt
py_dreambooth/scripts/infer/sd_dreambooth_lora/__init__.py
py_dreambooth/scripts/infer/sd_dreambooth_lora/inference.py
py_dreambooth/scripts/infer/sd_dreambooth_lora/requirements.txt
py_dreambooth/scripts/infer/sdxl_dreambooth_lora/__init__.py
py_dreambooth/scripts/infer/sdxl_dreambooth_lora/inference.py
py_dreambooth/scripts/infer/sdxl_dreambooth_lora/requirements.txt
py_dreambooth/scripts/train/__init__.py
py_dreambooth/scripts/train/requirements.txt
py_dreambooth/scripts/train/train_sd_dreambooth.py
py_dreambooth/scripts/train/train_sd_dreambooth_lora.py
py_dreambooth/scripts/train/train_sdxl_dreambooth_lora.py
py_dreambooth/utils/__init__.py
py_dreambooth/utils/aws_helpers.py
py_dreambooth/utils/image_helpers.py
py_dreambooth/utils/misc.py
py_dreambooth/utils/prompt_helpers.py
py_dreambooth-0.2.8.dist-info/LICENSE
py_dreambooth-0.2.8.dist-info/METADATA
py_dreambooth-0.2.8.dist-info/WHEEL
py_dreambooth-0.2.8.dist-info/top_level.txt
py_dreambooth-0.2.8.dist-info/RECORD
