Metadata-Version: 2.1
Name: py-dreambooth
Version: 0.2.8
Summary: Easily create your own AI avatar images!
Home-page: https://github.com/aldente0630/py-dreambooth
Author: Youngmin Kim
Author-email: aldente0630@gmail.com
License: creativeml-openrail-m
Classifier: Development Status :: 3 - Alpha
Classifier: Intended Audience :: Developers
Classifier: Natural Language :: English
Classifier: Programming Language :: Python
Classifier: Programming Language :: Python :: 3
Classifier: Programming Language :: Python :: 3.7
Classifier: Programming Language :: Python :: 3.8
Classifier: Programming Language :: Python :: 3.9
Classifier: Programming Language :: Python :: 3.10
Requires-Python: >=3.7.0
License-File: LICENSE
Requires-Dist: accelerate (>=0.23.0)
Requires-Dist: autocrop (>=1.3.0)
Requires-Dist: awscli (>=1.29.41)
Requires-Dist: bitsandbytes (>=0.41.0)
Requires-Dist: diffusers (>=0.24.0)
Requires-Dist: matplotlib (>=3.7.2)
Requires-Dist: peft (>=0.7.1)
Requires-Dist: pillow (>=9.4.0)
Requires-Dist: torch (==2.0.1)
Requires-Dist: torchvision (>=0.15.2)
Requires-Dist: sagemaker (>=2.183.0)
Requires-Dist: tensorboard (>=2.13.0)
Requires-Dist: tqdm (>=4.65.0)
Requires-Dist: transformers (>=4.33.2)
Requires-Dist: wandb (>=0.15.11)
Requires-Dist: xformers (>=0.0.20)
Provides-Extra: test
Requires-Dist: black ; extra == 'test'
Requires-Dist: coverage ; extra == 'test'
Requires-Dist: flake8 ; extra == 'test'
Requires-Dist: mock ; extra == 'test'
Requires-Dist: pydocstyle ; extra == 'test'
Requires-Dist: pytest ; extra == 'test'
Requires-Dist: pytest-cov ; extra == 'test'
Requires-Dist: tox ; extra == 'test'
